swarmcg/__init__.py
swarmcg/analyze_optimization.py
swarmcg/config.py
swarmcg/evaluate_model.py
swarmcg/optimize_model.py
swarmcg/swarmCG.py
swarmcg/shared/__init__.py
swarmcg/shared/exceptions.py
swarmcg/shared/io.py
swarmcg/shared/styling.py
swarmcg/shared/utils.py
swarmcg/simulations/__init__.py
swarmcg/simulations/potentials.py
swarmcg/simulations/vs_functions.py
swarm_cg-1.2.5.dist-info/LICENSE.txt
swarm_cg-1.2.5.dist-info/METADATA
swarm_cg-1.2.5.dist-info/WHEEL
swarm_cg-1.2.5.dist-info/entry_points.txt
swarm_cg-1.2.5.dist-info/top_level.txt
swarm_cg-1.2.5.dist-info/RECORD
