Metadata-Version: 2.1
Name: swarm-cg
Version: 1.2.5
Summary: Tools for automatic parametrization of bonded terms in coarse-grained molecular models, with respect to an all-atom trajectory
Home-page: https://github.com/GMPavanLab/Swarm-CG
Author: Charly Empereur-mot
Author-email: charly.empereur@gmail.com
License: MIT
Download-URL: https://github.com/GMPavanLab/Swarm-CG/archive/v1.2.5.tar.gz
Keywords: gromacs,coarse-grain,molecular model,optimization,force field
Platform: UNKNOWN
Classifier: Programming Language :: Python :: 3
Classifier: Programming Language :: Python :: 3.6
Requires-Dist: numpy (>=1.16.4)
Requires-Dist: scipy (>=1.2.2)
Requires-Dist: pyemd (>=0.5.1)
Requires-Dist: matplotlib (>=3.2.2)
Requires-Dist: fst-pso (>=1.4.12)
Requires-Dist: MDAnalysis (>=1.0.0)
